{"commitInfo":{"timestamp":1774630077070,"operation":"CREATE TABLE","operationParameters":{"partitionBy":"[]","clusterBy":"[]","description":null,"isManaged":"false","properties":"{}"},"isolationLevel":"Serializable","isBlindAppend":true,"operationMetrics":{},"engineInfo":"Apache-Spark/3.5.1 Delta-Lake/3.2.0","txnId":"d91cd479-5368-4f1c-845f-2c18665cbb63"}}
{"metaData":{"id":"0b12d409-6cd5-4015-9b75-8e3a9b7df430","format":{"provider":"parquet","options":{}},"schemaString":"{\"type\":\"struct\",\"fields\":[{\"name\":\"delivery_partner_sk\",\"type\":\"long\",\"nullable\":true,\"metadata\":{}},{\"name\":\"partner_id\",\"type\":\"string\",\"nullable\":true,\"metadata\":{}},{\"name\":\"partner_name\",\"type\":\"string\",\"nullable\":true,\"metadata\":{}},{\"name\":\"partner_type\",\"type\":\"string\",\"nullable\":true,\"metadata\":{}},{\"name\":\"effective_from\",\"type\":\"timestamp\",\"nullable\":true,\"metadata\":{}},{\"name\":\"effective_to\",\"type\":\"timestamp\",\"nullable\":true,\"metadata\":{}},{\"name\":\"is_current\",\"type\":\"boolean\",\"nullable\":true,\"metadata\":{}}]}","partitionColumns":[],"configuration":{},"createdTime":1774630076883}}
{"protocol":{"minReaderVersion":1,"minWriterVersion":2}}
